pipje/__init__.py
pipje/pipje.py
pipje-0.1.8.dist-info/METADATA
pipje-0.1.8.dist-info/WHEEL
pipje-0.1.8.dist-info/top_level.txt
pipje-0.1.8.dist-info/RECORD
